MANIFEST.in
README.rst
setup.py
cms_bs3_theme_solid/__init__.py
cms_bs3_theme_solid/static/cms_bs3_theme_solid/src/.sass-cache/3d07202c344f27614d47392ced5854d4ea0e7ffb/_alerts.scssc
cms_bs3_theme_solid/static/cms_bs3_theme_solid/src/.sass-cache/3d07202c344f27614d47392ced5854d4ea0e7ffb/_background-variant.scssc
cms_bs3_theme_solid/static/cms_bs3_theme_solid/src/.sass-cache/3d07202c344f27614d47392ced5854d4ea0e7ffb/_border-radius.scssc
cms_bs3_theme_solid/static/cms_bs3_theme_solid/src/.sass-cache/3d07202c344f27614d47392ced5854d4ea0e7ffb/_buttons.scssc
cms_bs3_theme_solid/static/cms_bs3_theme_solid/src/.sass-cache/3d07202c344f27614d47392ced5854d4ea0e7ffb/_center-block.scssc
cms_bs3_theme_solid/static/cms_bs3_theme_solid/src/.sass-cache/3d07202c344f27614d47392ced5854d4ea0e7ffb/_clearfix.scssc
cms_bs3_theme_solid/static/cms_bs3_theme_solid/src/.sass-cache/3d07202c344f27614d47392ced5854d4ea0e7ffb/_forms.scssc
cms_bs3_theme_solid/static/cms_bs3_theme_solid/src/.sass-cache/3d07202c344f27614d47392ced5854d4ea0e7ffb/_gradients.scssc
cms_bs3_theme_solid/static/cms_bs3_theme_solid/src/.sass-cache/3d07202c344f27614d47392ced5854d4ea0e7ffb/_grid-framework.scssc
cms_bs3_theme_solid/static/cms_bs3_theme_solid/src/.sass-cache/3d07202c344f27614d47392ced5854d4ea0e7ffb/_grid.scssc
cms_bs3_theme_solid/static/cms_bs3_theme_solid/src/.sass-cache/3d07202c344f27614d47392ced5854d4ea0e7ffb/_hide-text.scssc
cms_bs3_theme_solid/static/cms_bs3_theme_solid/src/.sass-cache/3d07202c344f27614d47392ced5854d4ea0e7ffb/_image.scssc
cms_bs3_theme_solid/static/cms_bs3_theme_solid/src/.sass-cache/3d07202c344f27614d47392ced5854d4ea0e7ffb/_labels.scssc
cms_bs3_theme_solid/static/cms_bs3_theme_solid/src/.sass-cache/3d07202c344f27614d47392ced5854d4ea0e7ffb/_list-group.scssc
cms_bs3_theme_solid/static/cms_bs3_theme_solid/src/.sass-cache/3d07202c344f27614d47392ced5854d4ea0e7ffb/_nav-divider.scssc
djangocms_bs3_theme_solid.egg-info/PKG-INFO
djangocms_bs3_theme_solid.egg-info/SOURCES.txt
djangocms_bs3_theme_solid.egg-info/dependency_links.txt
djangocms_bs3_theme_solid.egg-info/not-zip-safe
djangocms_bs3_theme_solid.egg-info/pbr.json
djangocms_bs3_theme_solid.egg-info/top_level.txt