Metadata-Version: 1.1
Name: djangocms-bs3-theme-solid
Version: 0.1.0
Summary: A comment system for Django CMS unintrusive and easy to use.
